hello/README.md
hello/__init__.py
hello/__main__.py
hello/data/__init__.py
hello/data/__main__.py
hello/data/coco2yolo.py
hello/experimental/__init__.py
hello/experimental/albu/__init__.py
hello/experimental/albu/detection.py
hello/fiftyone/__init__.py
hello/fiftyone/__main__.py
hello/fiftyone/annotate.py
hello/fiftyone/brain.py
hello/fiftyone/coco.py
hello/fiftyone/coco_utils.py
hello/fiftyone/connected.py
hello/fiftyone/copypaste.py
hello/fiftyone/core.py
hello/fiftyone/dataset.py
hello/fiftyone/dataset_detections.py
hello/fiftyone/dataset_segmentations.py
hello/fiftyone/dataset_yolov5.py
hello/fiftyone/dataset_zoo.py
hello/fiftyone/evaluate.py
hello/fiftyone/evaluate_detections.py
hello/fiftyone/evaluate_segmentations.py
hello/fiftyone/gen_examples.py
hello/fiftyone/mask_ignore.py
hello/fiftyone/miou.py
hello/fiftyone/patches.py
hello/fiftyone/tarinfo.py
hello/fiftyone/unique.py
hello/fiftyone/utils.py
hello/fiftyone/video.py
hello/fiftyone/view.py
hello/fiftyone/examples/README.md
hello/fiftyone/examples/examples.py
hello/fiftyone/examples/utils.py
hello/fiftyone/novabot/README.md
hello/fiftyone/novabot/big_test.py
hello/fiftyone/novabot/cal_data.py
hello/fiftyone/novabot/det_annotate.py
hello/fiftyone/novabot/det_big_train.py
hello/fiftyone/novabot/seg_base.py
hello/fiftyone/novabot/tag_data.py
hello/fvcore/README.md
hello/fvcore/__init__.py
hello/fvcore/core.py
hello/io/__init__.py
hello/io/image.py
hello/io/utils.py
hello/mmdet/__init__.py
hello/mmdet/__main__.py
hello/mmdet/export.py
hello/mmdet/flop.py
hello/mmdet/infer.py
hello/mmdet/log.py
hello/mmdet/plot.py
hello/mmlab/__init__.py
hello/mmlab/__main__.py
hello/mmlab/mmdet3.py
hello/mmlab/mmseg.py
hello/mmseg/__init__.py
hello/mmseg/__main__.py
hello/mmseg/infer.py
hello/mmseg/log.py
hello/mmseg/lr.py
hello/nanodet/__init__.py
hello/nanodet/__main__.py
hello/nanodet/infer.py
hello/onnx/__init__.py
hello/onnx/export.py
hello/onnx/infer.py
hello/onnx/examples/README.md
hello/onnx/examples/test_sigmoid.py
hello2-2.0.16.dist-info/entry_points.txt
hello2-2.0.16.dist-info/LICENSE
hello2-2.0.16.dist-info/WHEEL
hello2-2.0.16.dist-info/METADATA
hello2-2.0.16.dist-info/RECORD
