Metadata-Version: 2.1
Name: hello2
Version: 2.0.16
Summary: A collection of useful tools!
Author-email: Hejian <flystarhe@qq.com>
Requires-Python: >=3.6
Requires-Dist: opencv-python
Requires-Dist: Pillow
Requires-Dist: scikit-image
Requires-Dist: scikit-learn
Requires-Dist: simplejson
Requires-Dist: onnx
Project-URL: Home, https://github.com/flystarhe/hello
